namel3ss/__init__.py
namel3ss/api_inventory.py
namel3ss/ast_nodes.py
namel3ss/cli.py
namel3ss/config.py
namel3ss/deprecations.py
namel3ss/errors.py
namel3ss/ir.py
namel3ss/lexer.py
namel3ss/linting.py
namel3ss/macros.py
namel3ss/parser.py
namel3ss/server.py
namel3ss/typesys.py
namel3ss/version.py
namel3ss/agent/__init__.py
namel3ss/agent/debate.py
namel3ss/agent/engine.py
namel3ss/agent/evaluation.py
namel3ss/agent/evaluators.py
namel3ss/agent/models.py
namel3ss/agent/plan.py
namel3ss/agent/planning.py
namel3ss/agent/reflection.py
namel3ss/agent/teams.py
namel3ss/ai/__init__.py
namel3ss/ai/config.py
namel3ss/ai/embedding_router.py
namel3ss/ai/http_json_provider.py
namel3ss/ai/models.py
namel3ss/ai/openai_provider.py
namel3ss/ai/registry.py
namel3ss/ai/router.py
namel3ss/ai/embeddings/__init__.py
namel3ss/ai/embeddings/http_generic.py
namel3ss/ai/embeddings/openai.py
namel3ss/ai/providers/__init__.py
namel3ss/ai/providers/anthropic.py
namel3ss/ai/providers/azure_openai.py
namel3ss/ai/providers/gemini.py
namel3ss/ai/providers/generic_http.py
namel3ss/ai/providers/http_json.py
namel3ss/ai/providers/lmstudio.py
namel3ss/ai/providers/ollama.py
namel3ss/ai/providers/openai.py
namel3ss/ai/providers/openai_compatible.py
namel3ss/deploy/aws_lambda.py
namel3ss/deploy/builder.py
namel3ss/deploy/desktop.py
namel3ss/deploy/docker.py
namel3ss/deploy/mobile.py
namel3ss/deploy/models.py
namel3ss/deploy/server_entry.py
namel3ss/deploy/worker_entry.py
namel3ss/diagnostics/__init__.py
namel3ss/diagnostics/adapters.py
namel3ss/diagnostics/engine.py
namel3ss/diagnostics/models.py
namel3ss/diagnostics/pipeline.py
namel3ss/diagnostics/registry.py
namel3ss/diagnostics/runner.py
namel3ss/diagnostics/structured.py
namel3ss/distributed/__init__.py
namel3ss/distributed/file_watcher.py
namel3ss/distributed/models.py
namel3ss/distributed/queue.py
namel3ss/distributed/scheduler.py
namel3ss/distributed/workers.py
namel3ss/examples/catalog.py
namel3ss/examples/manager.py
namel3ss/flows/__init__.py
namel3ss-0.7.0.dist-info/METADATA
namel3ss-0.7.0.dist-info/WHEEL
namel3ss-0.7.0.dist-info/entry_points.txt
namel3ss-0.7.0.dist-info/licenses/LICENSE
namel3ss-0.7.0.dist-info/RECORD
