Metadata-Version: 2.4
Name: namel3ss
Version: 0.7.0
Summary: AI-native programming language with English-style syntax for building agents, flows, and UI
Project-URL: Homepage, https://namel3ss.ai
Project-URL: Documentation, https://namel3ss.ai/docs
Project-URL: Repository, https://github.com/namel3ss-Ai/namel3ss-ai-programming-language
Project-URL: Bug Tracker, https://github.com/namel3ss-Ai/namel3ss-ai-programming-language/issues
Project-URL: Changelog, https://github.com/namel3ss-Ai/namel3ss-ai-programming-language/blob/main/CHANGELOG.md
Author-email: Namel3ss Team <team@namel3ss.ai>
License: MIT
License-File: LICENSE
Keywords: agent,ai,ai-native,automation,dsl,flow,language,llm,programming-language,studio
Classifier: Development Status :: 4 - Beta
Classifier: Intended Audience :: Developers
Classifier: License :: OSI Approved :: MIT License
Classifier: Operating System :: OS Independent
Classifier: Programming Language :: Python :: 3
Classifier: Programming Language :: Python :: 3.11
Classifier: Programming Language :: Python :: 3.12
Classifier: Programming Language :: Python :: 3.13
Classifier: Topic :: Scientific/Engineering :: Artificial Intelligence
Classifier: Topic :: Software Development :: Compilers
Classifier: Topic :: Software Development :: Interpreters
Requires-Python: >=3.11
Requires-Dist: fastapi>=0.110.0
Requires-Dist: python-multipart>=0.0.9
Requires-Dist: uvicorn>=0.29.0
Provides-Extra: dev
Requires-Dist: black>=24.0.0; extra == 'dev'
Requires-Dist: httpx>=0.28.0; extra == 'dev'
Requires-Dist: isort>=5.13.0; extra == 'dev'
Requires-Dist: mkdocs>=1.5.3; extra == 'dev'
Requires-Dist: mypy>=1.10.0; extra == 'dev'
Requires-Dist: pytest-cov>=4.1.0; extra == 'dev'
Requires-Dist: pytest>=8.0.0; extra == 'dev'
Requires-Dist: ruff>=0.6.0; extra == 'dev'
